viggopayfac/__init__.py
viggopayfac/packages.py
viggopayfac/resources.py
viggopayfac/subsystem/__init__.py
viggopayfac/subsystem/controle/__init__.py
viggopayfac/subsystem/controle/configuracao_pay_fac/__init__.py
viggopayfac/subsystem/controle/configuracao_pay_fac/manager.py
viggopayfac/subsystem/controle/configuracao_pay_fac/resource.py
viggopayfac/subsystem/controle/configuracao_pay_fac/router.py
viggopayfac/subsystem/controle/pay_fac/__init__.py
viggopayfac/subsystem/controle/pay_fac/config_ambiente.py
viggopayfac/subsystem/controle/pay_fac/controller.py
viggopayfac/subsystem/controle/pay_fac/manager.py
viggopayfac/subsystem/controle/pay_fac/resource.py
viggopayfac/subsystem/controle/pay_fac/router.py
viggopayfac/subsystem/controle/pay_fac/transaction_hash.py
viggopayfac-1.0.17.dist-info/AUTHORS
viggopayfac-1.0.17.dist-info/LICENSE
viggopayfac-1.0.17.dist-info/METADATA
viggopayfac-1.0.17.dist-info/WHEEL
viggopayfac-1.0.17.dist-info/top_level.txt
viggopayfac-1.0.17.dist-info/RECORD
